AUTHORS.rst
CONTRIBUTING.rst
HISTORY.rst
LICENSE
MANIFEST.in
README.rst
setup.cfg
setup.py
bonvoyage/__init__.py
bonvoyage/utils.py
bonvoyage/visualize.py
bonvoyage/voyages.py
bonvoyage/waypoints.py
bonvoyage.egg-info/PKG-INFO
bonvoyage.egg-info/SOURCES.txt
bonvoyage.egg-info/dependency_links.txt
bonvoyage.egg-info/not-zip-safe
bonvoyage.egg-info/top_level.txt
docs/Makefile
docs/authors.rst
docs/conf.py
docs/contributing.rst
docs/history.rst
docs/index.rst
docs/installation.rst
docs/make.bat
docs/readme.rst
docs/tutorial.rst
docs/usage.rst
docs/releases/v0.1.0.rst